pycrutils/__init__.py
pycrutils/streams/__init__.py
pycrutils/streams/streams.py
pycrutils-0.0.0.dev2.dist-info/DESCRIPTION.rst
pycrutils-0.0.0.dev2.dist-info/METADATA
pycrutils-0.0.0.dev2.dist-info/RECORD
pycrutils-0.0.0.dev2.dist-info/WHEEL
pycrutils-0.0.0.dev2.dist-info/metadata.json
pycrutils-0.0.0.dev2.dist-info/top_level.txt
