Metadata-Version: 2.0
Name: pycrutils
Version: 0.0.0.dev2
Summary: A set of tools for a application developtment
Home-page: https://bitbucket.org/code-reapers/pycrutils/overview
Author: CodeReaper91
Author-email: codereaper91@gmail.com
License: MIT
Keywords: development
Platform: UNKNOWN
Requires-Python: >=3
